LICENSE
README.md
setup.cfg
setup.py
ccnalysis.egg-info/PKG-INFO
ccnalysis.egg-info/SOURCES.txt
ccnalysis.egg-info/dependency_links.txt
ccnalysis.egg-info/requires.txt
ccnalysis.egg-info/top_level.txt
pycat/AAC_data_extraction.py
pycat/Datafile_preprocessing.py
pycat/SMPSbased_CCNC_calibration.py
pycat/TF_analysis.py
pycat/__init__.py
pycat/functions_basic.py
pycat/version.py